dwpose/__init__.py
dwpose/animalpose.py
dwpose/body.py
dwpose/face.py
dwpose/hand.py
dwpose/model.py
dwpose/types.py
dwpose/util.py
dwpose/util2.py
dwpose/wholebody.py
dwpose/dw_onnx/__init__.py
dwpose/dw_onnx/cv_ox_det.py
dwpose/dw_onnx/cv_ox_pose.py
dwpose/dw_onnx/cv_ox_yolo_nas.py
dwpose/dw_torchscript/__init__.py
dwpose/dw_torchscript/jit_det.py
dwpose/dw_torchscript/jit_pose.py
dwpose-1.0.1.dist-info/LICENSE
dwpose-1.0.1.dist-info/METADATA
dwpose-1.0.1.dist-info/WHEEL
dwpose-1.0.1.dist-info/top_level.txt
dwpose-1.0.1.dist-info/RECORD
