Metadata-Version: 2.1
Name: dwpose
Version: 1.0.1
Summary: Easy DWPose Detector
Author-email: nicehero <85948597@qq.com>
Project-URL: Homepage, https://github.com/nicehero/dwpose
Project-URL: Issues, https://github.com/nicehero/dwpose/issues
Classifier: Programming Language :: Python :: 3
Classifier: License :: OSI Approved :: Apache Software License
Classifier: Operating System :: OS Independent
Requires-Python: >=3.9
License-File: LICENSE
